pybader/__init__.py
pybader/dunders.py
pybader/entry_points.py
pybader/interface.py
pybader/jits.py
pybader/methods.py
pybader/refinement.py
pybader/thread_handlers.py
pybader/utils.py
pybader/io/__init__.py
pybader/io/cube.py
pybader/io/gpaw.py
pybader/io/pymatgen.py
pybader/io/vasp.py
pybader-0.3.12.dist-info/LICENSE
pybader-0.3.12.dist-info/METADATA
pybader-0.3.12.dist-info/WHEEL
pybader-0.3.12.dist-info/entry_points.txt
pybader-0.3.12.dist-info/top_level.txt
pybader-0.3.12.dist-info/RECORD
