Metadata-Version: 2.1
Name: pybader
Version: 0.3.12
Summary: Threaded implementation of grid-based Bader charge analysis.
Home-page: https://github.com/kerrigoon/pybader
Author: Adam Kerrigan
Author-email: ak1014@york.ac.uk
License: MIT
Keywords: grid-based,Bader,charge,analysis
Platform: Linux
Platform: Unix
Platform: Mac OS-X
Platform: Windows
Classifier: Development Status :: 5 - Production/Stable
Classifier: Intended Audience :: Science/Research
Classifier: License :: OSI Approved
Classifier: License :: OSI Approved :: MIT License
Classifier: Natural Language :: English
Classifier: Programming Language :: Python
Classifier: Programming Language :: Python :: 3
Classifier: Programming Language :: Python :: 3.6
Classifier: Programming Language :: Python :: 3.7
Classifier: Programming Language :: Python :: 3.8
Classifier: Programming Language :: Python :: 3 :: Only
Classifier: Topic :: Scientific/Engineering
Classifier: Topic :: Scientific/Engineering :: Chemistry
Classifier: Topic :: Scientific/Engineering :: Physics
Classifier: Operating System :: Microsoft :: Windows
Classifier: Operating System :: POSIX
Classifier: Operating System :: Unix
Classifier: Operating System :: MacOS
Requires-Python: >=3.6
Requires-Dist: tqdm
Requires-Dist: numba
Requires-Dist: numpy
Requires-Dist: pandas
